amix/__init__.py
amix/amix.json
amix/amix.py
amix/cli.py
amix-0.1.7.dist-info/LICENSE.txt
amix-0.1.7.dist-info/METADATA
amix-0.1.7.dist-info/WHEEL
amix-0.1.7.dist-info/entry_points.txt
amix-0.1.7.dist-info/top_level.txt
amix-0.1.7.dist-info/RECORD
