Metadata-Version: 2.1
Name: amix
Version: 0.1.7
Summary: Automatic mix of audio clips.
Home-page: https://github.com/artificialhoney/amix/
Author: Sebastian Krüger
Author-email: sk@honeymachine.io
License: MIT
Project-URL: Documentation, https://artificialhoney.github.io/amix/
Project-URL: Source, https://github.com/artificialhoney/amix/
Project-URL: Tracker, https://github.com/artificialhoney/amix/issues
Project-URL: Download, https://pypi.org/project/amix/#files
Platform: any
Classifier: Development Status :: 4 - Beta
Classifier: Programming Language :: Python
License-File: LICENSE.txt
Requires-Dist: ffmpeg-python
Requires-Dist: jsonschema
Requires-Dist: jinja2
Requires-Dist: pyaml
Requires-Dist: importlib-metadata ; python_version < "3.8"
Provides-Extra: testing
Requires-Dist: setuptools ; extra == 'testing'
Requires-Dist: pytest ; extra == 'testing'
Requires-Dist: pytest-cov ; extra == 'testing'
